hmatrices/__init__.py
hmatrices/examples/simple_test.py
hmatrices-0.1.3.dist-info/METADATA
hmatrices-0.1.3.dist-info/WHEEL
hmatrices-0.1.3.dist-info/RECORD
