Metadata-Version: 2.1
Name: hmatrices
Version: 0.1.3
Summary: 
Author: Luiz M. Faria
Author-email: maltezfaria@gmail.com
Requires-Python: >=3.11,<4.0
Classifier: Programming Language :: Python :: 3
Classifier: Programming Language :: Python :: 3.11
Requires-Dist: juliacall (>=0.9.13,<0.10.0)
